ofxstatement_iso20022-0.8.1-py3.12-nspkg.pth
ofxstatement/plugins/iso20022.py
ofxstatement_iso20022-0.8.1.dist-info/METADATA
ofxstatement_iso20022-0.8.1.dist-info/WHEEL
ofxstatement_iso20022-0.8.1.dist-info/entry_points.txt
ofxstatement_iso20022-0.8.1.dist-info/namespace_packages.txt
ofxstatement_iso20022-0.8.1.dist-info/top_level.txt
ofxstatement_iso20022-0.8.1.dist-info/zip-safe
ofxstatement_iso20022-0.8.1.dist-info/RECORD
