Metadata-Version: 2.1
Name: ofxstatement-iso20022
Version: 0.8.1
Summary: ISO-20022 plugin for ofxstatement
Home-page: https://github.com/kedder/ofxstatement-iso20022
Author: Andrey Lebedev
Author-email: andrey@lebedev.lt
License: GPLv3
Keywords: ofx,banking,statement,iso-20022
Classifier: Development Status :: 3 - Alpha
Classifier: Programming Language :: Python :: 3
Classifier: Natural Language :: English
Classifier: Topic :: Office/Business :: Financial :: Accounting
Classifier: Topic :: Utilities
Classifier: Environment :: Console
Classifier: Operating System :: OS Independent
Classifier: License :: OSI Approved :: GNU Affero General Public License v3
Requires-Dist: ofxstatement
Provides-Extra: test
Requires-Dist: pytest; extra == "test"
